jarn.viewdoc-2.7-py3.11-nspkg.pth
jarn/viewdoc/__init__.py
jarn/viewdoc/__main__.py
jarn/viewdoc/colors.py
jarn/viewdoc/configparser.py
jarn/viewdoc/setup.py
jarn/viewdoc/testing.py
jarn/viewdoc/viewdoc.py
jarn.viewdoc-2.7.dist-info/LICENSE
jarn.viewdoc-2.7.dist-info/METADATA
jarn.viewdoc-2.7.dist-info/WHEEL
jarn.viewdoc-2.7.dist-info/entry_points.txt
jarn.viewdoc-2.7.dist-info/namespace_packages.txt
jarn.viewdoc-2.7.dist-info/top_level.txt
jarn.viewdoc-2.7.dist-info/RECORD
