Metadata-Version: 2.1
Name: jarn.viewdoc
Version: 2.7
Summary: Python documentation viewer
Home-page: https://github.com/Jarn/jarn.viewdoc
Author: Stefan H. Holek
Author-email: stefan@epy.co.at
License: BSD-2-Clause
Keywords: view,rest,rst,package,docs,documentation,rst2html,long-description
Classifier: Development Status :: 5 - Production/Stable
Classifier: Environment :: Console
Classifier: Intended Audience :: Developers
Classifier: License :: OSI Approved :: BSD License
Classifier: Operating System :: OS Independent
Classifier: Programming Language :: Python :: 2
Classifier: Programming Language :: Python :: 3
Requires-Python: !=3.0.*,!=3.1.*,!=3.2.*,!=3.3.*,>=2.7
License-File: LICENSE
Requires-Dist: setuptools
Requires-Dist: docutils
Requires-Dist: pygments
Requires-Dist: blessed
